{
"RECORDS":[
{
"member_id":1,
"sid":10019
},
{
"member_id":2,
"sid":10018
},
{
"member_id":3,
"sid":10001
},
{
"member_id":4,
"sid":10020
},
{
"member_id":5,
"sid":10017
},
{
"member_id":6,
"sid":10022
},
{
"member_id":7,
"sid":10023
},
{
"member_id":8,
"sid":10010
},
{
"member_id":9,
"sid":10011
},
{
"member_id":10,
"sid":10026
},
{
"member_id":11,
"sid":10012
},
{
"member_id":12,
"sid":10033
},
{
"member_id":13,
"sid":10028
},
{
"member_id":14,
"sid":10016
},
{
"member_id":15,
"sid":10032
},
{
"member_id":16,
"sid":10031
},
{
"member_id":17,
"sid":10004
},
{
"member_id":18,
"sid":10014
},
{
"member_id":19,
"sid":10005
},
{
"member_id":20,
"sid":10006
},
{
"member_id":21,
"sid":10015
},
{
"member_id":22,
"sid":10025
},
{
"member_id":24,
"sid":10029
},
{
"member_id":25,
"sid":10034
},
{
"member_id":26,
"sid":10024
},
{
"member_id":27,
"sid":10037
},
{
"member_id":28,
"sid":10057
},
{
"member_id":32,
"sid":10054
},
{
"member_id":33,
"sid":10036
},
{
"member_id":34,
"sid":10030
},
{
"member_id":35,
"sid":10007
},
{
"member_id":36,
"sid":10008
},
{
"member_id":37,
"sid":10002
},
{
"member_id":38,
"sid":10003
},
{
"member_id":39,
"sid":10013
},
{
"member_id":40,
"sid":10009
},
{
"member_id":43,
"sid":10069
},
{
"member_id":45,
"sid":10067
},
{
"member_id":46,
"sid":10063
},
{
"member_id":47,
"sid":10064
},
{
"member_id":48,
"sid":10027
},
{
"member_id":49,
"sid":10038
},
{
"member_id":53,
"sid":0
},
{
"member_id":63,
"sid":0
},
{
"member_id":67,
"sid":10073
},
{
"member_id":68,
"sid":10021
},
{
"member_id":1338,
"sid":0
},
{
"member_id":1544,
"sid":10062
},
{
"member_id":2470,
"sid":10068
},
{
"member_id":2508,
"sid":10075
},
{
"member_id":5526,
"sid":0
},
{
"member_id":5527,
"sid":0
},
{
"member_id":5560,
"sid":10051
},
{
"member_id":5561,
"sid":0
},
{
"member_id":5562,
"sid":10061
},
{
"member_id":5563,
"sid":10065
},
{
"member_id":5564,
"sid":10066
},
{
"member_id":5566,
"sid":10070
},
{
"member_id":5567,
"sid":10071
},
{
"member_id":5574,
"sid":10076
},
{
"member_id":5973,
"sid":0
},
{
"member_id":6429,
"sid":10077
},
{
"member_id":6431,
"sid":10081
},
{
"member_id":6432,
"sid":10082
},
{
"member_id":6734,
"sid":10083
},
{
"member_id":6735,
"sid":10084
},
{
"member_id":6736,
"sid":0
},
{
"member_id":6737,
"sid":10086
},
{
"member_id":6738,
"sid":10087
},
{
"member_id":6739,
"sid":10088
},
{
"member_id":6740,
"sid":10089
},
{
"member_id":6741,
"sid":10090
},
{
"member_id":6742,
"sid":10091
},
{
"member_id":6743,
"sid":10092
},
{
"member_id":6744,
"sid":10093
},
{
"member_id":6745,
"sid":20019
},
{
"member_id":6746,
"sid":10095
},
{
"member_id":6747,
"sid":10096
},
{
"member_id":6749,
"sid":0
},
{
"member_id":9073,
"sid":0
},
{
"member_id":48995,
"sid":0
},
{
"member_id":48997,
"sid":0
},
{
"member_id":48998,
"sid":20016
},
{
"member_id":49000,
"sid":0
},
{
"member_id":49003,
"sid":10103
},
{
"member_id":49005,
"sid":10104
},
{
"member_id":49006,
"sid":50031
},
{
"member_id":49007,
"sid":10106
},
{
"member_id":63548,
"sid":30001
},
{
"member_id":63549,
"sid":20001
},
{
"member_id":63550,
"sid":10109
},
{
"member_id":63551,
"sid":10110
},
{
"member_id":63552,
"sid":30002
},
{
"member_id":63553,
"sid":30003
},
{
"member_id":63554,
"sid":20003
},
{
"member_id":63555,
"sid":10114
},
{
"member_id":63556,
"sid":20004
},
{
"member_id":63557,
"sid":30004
},
{
"member_id":63558,
"sid":10117
},
{
"member_id":63559,
"sid":20006
},
{
"member_id":63560,
"sid":10119
},
{
"member_id":63561,
"sid":10120
},
{
"member_id":63562,
"sid":30007
},
{
"member_id":63563,
"sid":30008
},
{
"member_id":63564,
"sid":30006
},
{
"member_id":63565,
"sid":30009
},
{
"member_id":63566,
"sid":10125
},
{
"member_id":63567,
"sid":10126
},
{
"member_id":63568,
"sid":20012
},
{
"member_id":63569,
"sid":0
},
{
"member_id":63570,
"sid":10129
},
{
"member_id":63571,
"sid":20013
},
{
"member_id":63572,
"sid":30012
},
{
"member_id":63573,
"sid":20017
},
{
"member_id":63574,
"sid":10133
},
{
"member_id":63575,
"sid":10134
},
{
"member_id":63576,
"sid":30013
},
{
"member_id":63577,
"sid":30014
},
{
"member_id":63578,
"sid":20020
},
{
"member_id":63579,
"sid":10138
},
{
"member_id":63580,
"sid":30015
},
{
"member_id":63581,
"sid":10140
},
{
"member_id":63582,
"sid":10141
},
{
"member_id":68795,
"sid":0
},
{
"member_id":286973,
"sid":10142
},
{
"member_id":286974,
"sid":0
},
{
"member_id":286975,
"sid":0
},
{
"member_id":286976,
"sid":10144
},
{
"member_id":286977,
"sid":10146
},
{
"member_id":286978,
"sid":40035
},
{
"member_id":286979,
"sid":10149
},
{
"member_id":286980,
"sid":10148
},
{
"member_id":286982,
"sid":10152
},
{
"member_id":286983,
"sid":10151
},
{
"member_id":286984,
"sid":0
},
{
"member_id":327557,
"sid":30005
},
{
"member_id":327558,
"sid":30010
},
{
"member_id":327559,
"sid":0
},
{
"member_id":327560,
"sid":30016
},
{
"member_id":327561,
"sid":30017
},
{
"member_id":327562,
"sid":30019
},
{
"member_id":327563,
"sid":30020
},
{
"member_id":327564,
"sid":30021
},
{
"member_id":327565,
"sid":30022
},
{
"member_id":327566,
"sid":30023
},
{
"member_id":327567,
"sid":30024
},
{
"member_id":327568,
"sid":30025
},
{
"member_id":327569,
"sid":30026
},
{
"member_id":327570,
"sid":30027
},
{
"member_id":327571,
"sid":30028
},
{
"member_id":327572,
"sid":30029
},
{
"member_id":327573,
"sid":30030
},
{
"member_id":327574,
"sid":30031
},
{
"member_id":327575,
"sid":30032
},
{
"member_id":327576,
"sid":30033
},
{
"member_id":327577,
"sid":30034
},
{
"member_id":327578,
"sid":20008
},
{
"member_id":327579,
"sid":20007
},
{
"member_id":327580,
"sid":20021
},
{
"member_id":327581,
"sid":20010
},
{
"member_id":327582,
"sid":20011
},
{
"member_id":327583,
"sid":20014
},
{
"member_id":327584,
"sid":20005
},
{
"member_id":327585,
"sid":20018
},
{
"member_id":327586,
"sid":20009
},
{
"member_id":327587,
"sid":20025
},
{
"member_id":327588,
"sid":20023
},
{
"member_id":327589,
"sid":20031
},
{
"member_id":327590,
"sid":20022
},
{
"member_id":327591,
"sid":20033
},
{
"member_id":327592,
"sid":20032
},
{
"member_id":327593,
"sid":20029
},
{
"member_id":327594,
"sid":20030
},
{
"member_id":327595,
"sid":20040
},
{
"member_id":327596,
"sid":20034
},
{
"member_id":327597,
"sid":20035
},
{
"member_id":327598,
"sid":20039
},
{
"member_id":327599,
"sid":20026
},
{
"member_id":327600,
"sid":20036
},
{
"member_id":327601,
"sid":20024
},
{
"member_id":327602,
"sid":20028
},
{
"member_id":327603,
"sid":20038
},
{
"member_id":327682,
"sid":0
},
{
"member_id":327683,
"sid":0
},
{
"member_id":399631,
"sid":10153
},
{
"member_id":399652,
"sid":10154
},
{
"member_id":399654,
"sid":10155
},
{
"member_id":399657,
"sid":10160
},
{
"member_id":399662,
"sid":10156
},
{
"member_id":399664,
"sid":10157
},
{
"member_id":399665,
"sid":10161
},
{
"member_id":399667,
"sid":10158
},
{
"member_id":399668,
"sid":10159
},
{
"member_id":399669,
"sid":10163
},
{
"member_id":399672,
"sid":10164
},
{
"member_id":399673,
"sid":10170
},
{
"member_id":399674,
"sid":10167
},
{
"member_id":407071,
"sid":20015
},
{
"member_id":407077,
"sid":20002
},
{
"member_id":407101,
"sid":20041
},
{
"member_id":407103,
"sid":20042
},
{
"member_id":407104,
"sid":20043
},
{
"member_id":407106,
"sid":20044
},
{
"member_id":407108,
"sid":20045
},
{
"member_id":407110,
"sid":20046
},
{
"member_id":407112,
"sid":20047
},
{
"member_id":407114,
"sid":20048
},
{
"member_id":407118,
"sid":20049
},
{
"member_id":407119,
"sid":20050
},
{
"member_id":407121,
"sid":20051
},
{
"member_id":407124,
"sid":20054
},
{
"member_id":407126,
"sid":20055
},
{
"member_id":407127,
"sid":20056
},
{
"member_id":407130,
"sid":20057
},
{
"member_id":407132,
"sid":20027
},
{
"member_id":407135,
"sid":20037
},
{
"member_id":407168,
"sid":20052
},
{
"member_id":410175,
"sid":30036
},
{
"member_id":410177,
"sid":30035
},
{
"member_id":410179,
"sid":0
},
{
"member_id":410180,
"sid":30038
},
{
"member_id":411040,
"sid":0
},
{
"member_id":417311,
"sid":30048
},
{
"member_id":417315,
"sid":30052
},
{
"member_id":417316,
"sid":30044
},
{
"member_id":417317,
"sid":30040
},
{
"member_id":417318,
"sid":30039
},
{
"member_id":417320,
"sid":30054
},
{
"member_id":417321,
"sid":30043
},
{
"member_id":417324,
"sid":30050
},
{
"member_id":417325,
"sid":30055
},
{
"member_id":417326,
"sid":30042
},
{
"member_id":417328,
"sid":30049
},
{
"member_id":417329,
"sid":30041
},
{
"member_id":417330,
"sid":30047
},
{
"member_id":417331,
"sid":30046
},
{
"member_id":417332,
"sid":30056
},
{
"member_id":417333,
"sid":30045
},
{
"member_id":417335,
"sid":30051
},
{
"member_id":417336,
"sid":30053
},
{
"member_id":419966,
"sid":10165
},
{
"member_id":443031,
"sid":0
},
{
"member_id":443032,
"sid":0
},
{
"member_id":444081,
"sid":20053
},
{
"member_id":458335,
"sid":40006
},
{
"member_id":458358,
"sid":40011
},
{
"member_id":459988,
"sid":40015
},
{
"member_id":459989,
"sid":40014
},
{
"member_id":459991,
"sid":40009
},
{
"member_id":459992,
"sid":40008
},
{
"member_id":459993,
"sid":40007
},
{
"member_id":459994,
"sid":40012
},
{
"member_id":459995,
"sid":40010
},
{
"member_id":459996,
"sid":40004
},
{
"member_id":459997,
"sid":40018
},
{
"member_id":459999,
"sid":40005
},
{
"member_id":460000,
"sid":40001
},
{
"member_id":460002,
"sid":40003
},
{
"member_id":460003,
"sid":40002
},
{
"member_id":460004,
"sid":40016
},
{
"member_id":460005,
"sid":40017
},
{
"member_id":460007,
"sid":40013
},
{
"member_id":460933,
"sid":0
},
{
"member_id":480656,
"sid":40019
},
{
"member_id":480665,
"sid":40020
},
{
"member_id":480666,
"sid":40021
},
{
"member_id":480667,
"sid":40022
},
{
"member_id":480668,
"sid":40023
},
{
"member_id":480670,
"sid":40024
},
{
"member_id":480671,
"sid":40025
},
{
"member_id":480672,
"sid":40026
},
{
"member_id":480673,
"sid":40027
},
{
"member_id":480674,
"sid":40028
},
{
"member_id":480675,
"sid":40029
},
{
"member_id":480676,
"sid":40030
},
{
"member_id":480678,
"sid":40031
},
{
"member_id":480679,
"sid":40032
},
{
"member_id":480680,
"sid":40033
},
{
"member_id":485376,
"sid":0
},
{
"member_id":485380,
"sid":0
},
{
"member_id":485381,
"sid":0
},
{
"member_id":490327,
"sid":0
},
{
"member_id":490333,
"sid":0
},
{
"member_id":524597,
"sid":0
},
{
"member_id":526172,
"sid":0
},
{
"member_id":528094,
"sid":20058
},
{
"member_id":528101,
"sid":20059
},
{
"member_id":528106,
"sid":20060
},
{
"member_id":528118,
"sid":20061
},
{
"member_id":528329,
"sid":20062
},
{
"member_id":528330,
"sid":20063
},
{
"member_id":528331,
"sid":20064
},
{
"member_id":528332,
"sid":20065
},
{
"member_id":528333,
"sid":20066
},
{
"member_id":528334,
"sid":20067
},
{
"member_id":528335,
"sid":20068
},
{
"member_id":528336,
"sid":20069
},
{
"member_id":528337,
"sid":20070
},
{
"member_id":528339,
"sid":20071
},
{
"member_id":528340,
"sid":20072
},
{
"member_id":529287,
"sid":0
},
{
"member_id":529991,
"sid":40036
},
{
"member_id":530378,
"sid":40037
},
{
"member_id":530380,
"sid":40038
},
{
"member_id":530381,
"sid":40039
},
{
"member_id":530383,
"sid":40040
},
{
"member_id":530384,
"sid":40041
},
{
"member_id":530385,
"sid":40042
},
{
"member_id":530386,
"sid":40043
},
{
"member_id":530387,
"sid":40044
},
{
"member_id":530388,
"sid":40045
},
{
"member_id":530390,
"sid":40046
},
{
"member_id":530392,
"sid":40047
},
{
"member_id":530431,
"sid":30057
},
{
"member_id":530433,
"sid":30058
},
{
"member_id":530434,
"sid":30059
},
{
"member_id":530435,
"sid":30060
},
{
"member_id":530436,
"sid":30061
},
{
"member_id":530439,
"sid":30062
},
{
"member_id":530440,
"sid":30063
},
{
"member_id":530443,
"sid":30065
},
{
"member_id":530444,
"sid":30066
},
{
"member_id":530446,
"sid":30067
},
{
"member_id":530447,
"sid":30068
},
{
"member_id":530450,
"sid":30069
},
{
"member_id":530451,
"sid":30070
},
{
"member_id":530452,
"sid":30071
},
{
"member_id":530584,
"sid":10171
},
{
"member_id":533852,
"sid":10177
},
{
"member_id":534729,
"sid":10172
},
{
"member_id":538697,
"sid":20073
},
{
"member_id":538735,
"sid":10178
},
{
"member_id":540106,
"sid":10173
},
{
"member_id":541132,
"sid":10176
},
{
"member_id":565225,
"sid":0
},
{
"member_id":592320,
"sid":10183
},
{
"member_id":592348,
"sid":10184
},
{
"member_id":593820,
"sid":10175
},
{
"member_id":593999,
"sid":10179
},
{
"member_id":594002,
"sid":10180
},
{
"member_id":594003,
"sid":10181
},
{
"member_id":594005,
"sid":10182
},
{
"member_id":601302,
"sid":30079
},
{
"member_id":606343,
"sid":10185
},
{
"member_id":607507,
"sid":30072
},
{
"member_id":607510,
"sid":30073
},
{
"member_id":607511,
"sid":30074
},
{
"member_id":607513,
"sid":30075
},
{
"member_id":607515,
"sid":0
},
{
"member_id":607516,
"sid":30077
},
{
"member_id":607521,
"sid":30078
},
{
"member_id":607523,
"sid":30080
},
{
"member_id":607524,
"sid":30081
},
{
"member_id":607591,
"sid":0
},
{
"member_id":607592,
"sid":0
},
{
"member_id":607594,
"sid":30084
},
{
"member_id":608995,
"sid":40048
},
{
"member_id":608997,
"sid":40049
},
{
"member_id":609001,
"sid":40050
},
{
"member_id":609002,
"sid":40051
},
{
"member_id":610040,
"sid":40054
},
{
"member_id":610042,
"sid":40053
},
{
"member_id":614528,
"sid":50001
},
{
"member_id":614725,
"sid":50002
},
{
"member_id":614727,
"sid":50003
},
{
"member_id":614728,
"sid":50004
},
{
"member_id":614729,
"sid":50005
},
{
"member_id":614730,
"sid":50006
},
{
"member_id":614731,
"sid":50007
},
{
"member_id":614733,
"sid":50008
},
{
"member_id":614734,
"sid":50009
},
{
"member_id":614735,
"sid":50010
},
{
"member_id":614736,
"sid":50011
},
{
"member_id":614738,
"sid":50012
},
{
"member_id":614739,
"sid":50013
},
{
"member_id":614740,
"sid":50014
},
{
"member_id":614741,
"sid":50016
},
{
"member_id":614742,
"sid":50017
},
{
"member_id":614743,
"sid":50018
},
{
"member_id":614749,
"sid":50019
},
{
"member_id":614750,
"sid":50020
},
{
"member_id":614752,
"sid":50021
},
{
"member_id":614753,
"sid":50022
},
{
"member_id":614754,
"sid":50023
},
{
"member_id":614755,
"sid":50024
},
{
"member_id":614756,
"sid":50026
},
{
"member_id":614757,
"sid":50027
},
{
"member_id":614758,
"sid":50028
},
{
"member_id":614760,
"sid":50029
},
{
"member_id":614761,
"sid":50032
},
{
"member_id":614762,
"sid":50033
},
{
"member_id":614770,
"sid":50034
},
{
"member_id":614772,
"sid":50035
},
{
"member_id":614773,
"sid":50036
},
{
"member_id":614776,
"sid":50030
},
{
"member_id":617948,
"sid":20077
},
{
"member_id":618319,
"sid":40052
},
{
"member_id":623828,
"sid":20078
},
{
"member_id":623832,
"sid":20079
},
{
"member_id":624121,
"sid":20080
},
{
"member_id":624311,
"sid":30085
},
{
"member_id":624312,
"sid":30086
},
{
"member_id":624313,
"sid":30087
},
{
"member_id":624314,
"sid":30088
},
{
"member_id":624315,
"sid":30089
},
{
"member_id":624318,
"sid":30090
},
{
"member_id":652650,
"sid":20081
},
{
"member_id":652652,
"sid":20082
},
{
"member_id":654707,
"sid":0
},
{
"member_id":677395,
"sid":10186
},
{
"member_id":677396,
"sid":10187
},
{
"member_id":677397,
"sid":10188
},
{
"member_id":677398,
"sid":10189
},
{
"member_id":677399,
"sid":10191
},
{
"member_id":677400,
"sid":10192
},
{
"member_id":677401,
"sid":10193
},
{
"member_id":677402,
"sid":10194
},
{
"member_id":677403,
"sid":10195
},
{
"member_id":677404,
"sid":10196
},
{
"member_id":677405,
"sid":10197
},
{
"member_id":677406,
"sid":10198
},
{
"member_id":679448,
"sid":40055
},
{
"member_id":679455,
"sid":40056
},
{
"member_id":679459,
"sid":40057
},
{
"member_id":679462,
"sid":40058
},
{
"member_id":679464,
"sid":40059
},
{
"member_id":679466,
"sid":40060
},
{
"member_id":679467,
"sid":40061
},
{
"member_id":707365,
"sid":50037
},
{
"member_id":707367,
"sid":50038
},
{
"member_id":707369,
"sid":50039
},
{
"member_id":707371,
"sid":50040
},
{
"member_id":707372,
"sid":50041
},
{
"member_id":707373,
"sid":50042
},
{
"member_id":707374,
"sid":50043
},
{
"member_id":707375,
"sid":50044
},
{
"member_id":711725,
"sid":0
},
{
"member_id":711726,
"sid":0
},
{
"member_id":711728,
"sid":0
},
{
"member_id":711730,
"sid":0
},
{
"member_id":711732,
"sid":0
},
{
"member_id":711735,
"sid":0
},
{
"member_id":711739,
"sid":0
},
{
"member_id":711741,
"sid":0
},
{
"member_id":711745,
"sid":0
},
{
"member_id":711746,
"sid":0
},
{
"member_id":722778,
"sid":0
},
{
"member_id":722780,
"sid":0
},
{
"member_id":722781,
"sid":0
},
{
"member_id":722782,
"sid":0
},
{
"member_id":722784,
"sid":0
},
{
"member_id":722787,
"sid":0
}
]
}